listupy/__init__.py
listupy/test.py
listupy/parts/test_python_file.py
listupy-0.1.0.dist-info/METADATA
listupy-0.1.0.dist-info/WHEEL
listupy-0.1.0.dist-info/entry_points.txt
listupy-0.1.0.dist-info/top_level.txt
listupy-0.1.0.dist-info/RECORD
