Metadata-Version: 2.1
Name: listupy
Version: 0.1.0
Summary: A tool that recursively enumerates Python files within a folder, calculates the total number of lines, and compiles them into a single Markdown text.
Home-page: https://github.co.jp/
Author: bib_inf
Author-email: contact.bibinf@gmail.com
License: CC0 v1.0
Platform: UNKNOWN
Classifier: Programming Language :: Python :: 3
Classifier: Topic :: Software Development :: Libraries
Classifier: License :: CC0 1.0 Universal (CC0 1.0) Public Domain Dedication
Requires-Dist: relpath
Requires-Dist: ezpip
Requires-Dist: sout
Requires-Dist: fies
